hastygram/__init__.py
hastygram/api.py
hastygram/app.py
hastygram-1.0.0.dist-info/LICENSE
hastygram-1.0.0.dist-info/METADATA
hastygram-1.0.0.dist-info/WHEEL
hastygram-1.0.0.dist-info/top_level.txt
hastygram-1.0.0.dist-info/RECORD
