Metadata-Version: 2.1
Name: hastygram
Version: 1.0.0
Summary: An lightweight frontend for Instagram
Home-page: https://github.com/zopieux/hastygram
Author: Alexandre Macabies
Author-email: web+oss@zopieux.com
License: UNKNOWN
Platform: UNKNOWN
Classifier: Programming Language :: Python :: 3
Classifier: License :: OSI Approved :: GNU General Public License v3 or later (GPLv3+)
Classifier: Operating System :: OS Independent
Requires-Python: >=3.7
Requires-Dist: fastapi (~=0.63)
Requires-Dist: aiohttp (~=3.7)
